beangulp/__init__.py
beangulp/archive.py
beangulp/archive_test.py
beangulp/cache.py
beangulp/cache_test.py
beangulp/csv_utils.py
beangulp/csv_utils_test.py
beangulp/date_utils.py
beangulp/date_utils_test.py
beangulp/exceptions.py
beangulp/extract.py
beangulp/extract_test.py
beangulp/file_type.py
beangulp/file_type_test.py
beangulp/identify.py
beangulp/identify_test.py
beangulp/importer.py
beangulp/importer_test.py
beangulp/mimetypes.py
beangulp/petl_utils.py
beangulp/petl_utils_test.py
beangulp/scripts_utils.py
beangulp/similar.py
beangulp/similar_test.py
beangulp/testing.py
beangulp/utils.py
beangulp/utils_test.py
beangulp/file_type_testdata/example.py
beangulp/importers/__init__.py
beangulp/importers/config.py
beangulp/importers/config_test.py
beangulp/importers/csv.py
beangulp/importers/csv_test.py
beangulp/importers/csvbase.py
beangulp/importers/csvbase_test.py
beangulp/importers/fileonly.py
beangulp/importers/fileonly_test.py
beangulp/importers/mixins/__init__.py
beangulp/importers/mixins/config.py
beangulp/importers/mixins/filing.py
beangulp/importers/mixins/identifier.py
beangulp/tests/__init__.py
beangulp/tests/doctests_test.py
beangulp/tests/utils.py
examples/import.py
examples/importers/__init__.py
examples/importers/acme.py
examples/importers/csvbank.py
examples/importers/ofx.py
examples/importers/utrade.py
examples/importers/tests/__init__.py
examples/importers/tests/test_ofx.py
tools/migrate_files.py
beangulp-0.2.0.dist-info/LICENSE
beangulp-0.2.0.dist-info/METADATA
beangulp-0.2.0.dist-info/WHEEL
beangulp-0.2.0.dist-info/top_level.txt
beangulp-0.2.0.dist-info/RECORD
