Metadata-Version: 2.2
Name: beangulp
Version: 0.2.0
Summary: Importers Framework for Beancount
Author-email: Martin Blais <blais@furius.ca>, Daniele Nicolodi <daniele@grinta.net>
Maintainer-email: Daniele Nicolodi <daniele@grinta.net>
License:                     GNU GENERAL PUBLIC LICENSE
Project-URL: homepage, https://github.com/beancount/beangulp
Project-URL: issues, https://github.com/beancount/beangulp/issues
Keywords: accounting,ledger,beancount,importer,import,converter,conversion
Classifier: License :: OSI Approved :: GNU General Public License v2 (GPLv2)
Classifier: Programming Language :: Python :: 3 :: Only
Classifier: Programming Language :: Python :: 3.8
Classifier: Programming Language :: Python :: 3.9
Classifier: Programming Language :: Python :: 3.10
Classifier: Programming Language :: Python :: 3.11
Classifier: Programming Language :: Python :: 3.12
Classifier: Programming Language :: Python :: 3.13
Classifier: Topic :: Office/Business :: Financial :: Accounting
Classifier: Topic :: Text Processing :: General
License-File: LICENSE
Requires-Dist: beancount>=2.3.5
Requires-Dist: beautifulsoup4
Requires-Dist: chardet
Requires-Dist: click>8.0
Requires-Dist: lxml
Requires-Dist: python-magic>=0.4.12; sys_platform != "win32"
